archus/__init__.py
archus/cli.py
archus/main.py
archus/request.py
archus/response.py
archus/router.py
archus/status.py
archus/core/__init__.py
archus/core/dependency.py
archus/docs/__init__.py
archus/docs/index.html
archus/docs/serve.py
archus/exceptions/__init__.py
archus/exceptions/main.py
archus/file_handlers/__init__.py
archus/file_handlers/file_parser.py
archus/file_handlers/media_handler.py
archus/file_handlers/static_handles.py
archus/mail/__init__.py
archus/mail/main.py
archus/middleware/CSPMiddleWare.py
archus/middleware/CorsMiddleware.py
archus/middleware/GlobalExceptionMiddleware.py
archus/middleware/LoggingMiddleware.py
archus/middleware/SecurityMiddleware.py
archus/middleware/ThrottleMiddleware.py
archus/middleware/__init__.py
archus/middleware/main.py
archus/middleware/order_middleware.py
archus/serializer/__init__.py
archus/serializer/field.py
archus/serializer/main.py
archus/serializer/validation_error.py
archus/template/__init__.py
archus/template/render.py
archus-1.2.0.dist-info/METADATA
archus-1.2.0.dist-info/WHEEL
archus-1.2.0.dist-info/entry_points.txt
archus-1.2.0.dist-info/top_level.txt
archus-1.2.0.dist-info/RECORD
