Metadata-Version: 2.1
Name: archus
Version: 1.2.0
Summary: A modern Python web framework designed to simplify your development process.
Home-page: https://github.com/Utsavch189/Archus-Framework
Author: Utsav Chatterjee
Author-email: utsavchatterjee71@gmail.com
License: MIT
Platform: UNKNOWN
Classifier: License :: OSI Approved :: MIT License
Classifier: Programming Language :: Python :: 3.10
Classifier: Operating System :: OS Independent
Requires-Python: >=3.10
Requires-Dist: Jinja2
Requires-Dist: gunicorn
Requires-Dist: waitress
